{
 "request": "Give me list of data plots for slide part\"Product/Service growth projection\" formatted in json as: data name, array of data series. Title of slide is Product/Service Description. Slide description is:Describe your product or service in detail, including its benefits, features and potential demand.Presentation description is :Bissness presentation for investors. My idea is automation of presentation. You just type your idea then software propose your steps to create presentation and try to automatize it.",
 "responses": [
  "{\n  Title: \"Product/Service Description\",\n  Description: \"Describe your product or service in detail, including its benefits, features and potential demand.\",\n  Plots: [\n    {\n      \"DataName\": \"Product/Service Growth Projection\",\n      \"DataSeries\": [\n        {\"Year\": \"2020\", \"Value\": 10000},\n        {\"Year\": \"2021\", \"Value\": 15000},\n        {\"Year\": \"2022\", \"Value\": 25000},\n        {\"Year\": \"2023\", \"Value\": 40000},\n        {\"Year\": \"2024\", \"Value\": 60000}\n      ]\n    },\n    {\n      \"DataName\": \"Projected Revenue\",\n      \"DataSeries\": [\n        {\"Year\": \"2020\", \"Value\": 100000},\n        {\"Year\": \"2021\", \"Value\": 150000},\n        {\"Year\": \"2022\", \"Value\": 250000},\n        {\"Year\": \"2023\", \"Value\": 400000},\n        {\"Year\": \"2024\", \"Value\": 600000}\n      ]\n    },\n    {\n      \"DataName\": \"Market Share\",\n      \"DataSeries\": [\n        {\"Year\": \"2020\", \"Value\": 5},\n        {\"Year\": \"2021\", \"Value\": 8},\n        {\"Year\": \"2022\", \"Value\": 12},\n        {\"Year\": \"2023\", \"Value\": 18},\n        {\"Year\": \"2024\", \"Value\": 25}\n      ]\n    }\n  ]\n}"
 ]
}